{
  "$schema": "http://json-schema.org/draft-04/schema#",
  "id": "http://justice.gov.uk/core/courts/external/apiCourtApplicationParty.json",
  "description": "The applicant or respondent of an application",
  "type": "object",
  "properties": {
    "id": {
      "$ref": "http://justice.gov.uk/core/courts/external/apiCourtsDefinitions.json#/definitions/uuid"
    },
    "synonym": {
      "description": "Provides the additional business persona of an applicant or respondent e.g. appellant, complainant, appellee, suspect",
      "type": "string"
    },
    "summonsRequired": {
      "description": "Indicates if this party is required to be summonsed.  Typically applies to the subject of the application",
      "type": "boolean"
    },
    "notificationRequired": {
      "description": "Indicates if this party is required to be notified of the application proceedings",
      "type": "boolean"
    },
    "appointmentNotificationRequired": {
      "description": "Indicates if this party is required to be notified of the application proceedings that are planned by telephone appointment.  Typically applies to the subject of the application",
      "type": "boolean"
    },
    "personDetails": {
      "description": "Provided when the party is a person",
      "$ref": "http://justice.gov.uk/core/courts/external/apiPerson.json"
    },
    "organisation": {
      "description": "Provided when the party is an organisation",
      "$ref": "http://justice.gov.uk/core/courts/external/apiOrganisation.json"
    },
    "organisationPersons": {
      "description": "Provided when the party is an organisation",
      "type": "array",
      "minItems": 1,
      "items": {
        "$ref": "http://justice.gov.uk/core/courts/external/apiAssociatedPerson.json"
      }
    },
    "prosecutingAuthority": {
      "description": "Provided when the party is a prosecutingAuthority for a linked case",
      "$ref": "http://justice.gov.uk/core/courts/external/apiProsecutingAuthority.json"
    },
    "masterDefendant": {
      "description": "Provided when the party is a defendant for a linked case",
      "$ref": "http://justice.gov.uk/core/courts/external/apiMasterDefendant.json"
    },
    "representationOrganisation": {
      "description": "The organisation details of the appointed representation",
      "$ref": "http://justice.gov.uk/core/courts/external/apiOrganisation.json"
    }
  },
  "required": [
    "id",
    "summonsRequired",
    "notificationRequired"
  ],
  "additionalProperties": false
}